xhs_bailian_mcp_server_jxh/__init__.py
xhs_bailian_mcp_server_jxh/server.py
xhs_bailian_mcp_server_jxh-0.2.0.dist-info/METADATA
xhs_bailian_mcp_server_jxh-0.2.0.dist-info/WHEEL
xhs_bailian_mcp_server_jxh-0.2.0.dist-info/entry_points.txt
xhs_bailian_mcp_server_jxh-0.2.0.dist-info/RECORD
