Metadata-Version: 2.4
Name: xhs-bailian-mcp-server_jxh
Version: 0.2.0
Summary: Add your description here
Requires-Python: >=3.10
Requires-Dist: bs4>=0.0.2
Requires-Dist: dashscope>=1.23.3
Requires-Dist: dotenv>=0.9.9
Requires-Dist: httpx>=0.28.1
Requires-Dist: mcp[cli]>=1.9.1
